LICENCE.txt
MANIFEST.in
README.md
__init__.py
setup.cfg
setup.py
conf/servers.json
gnsstoolbox/__init__.py
gnsstoolbox/antex.py
gnsstoolbox/gnss_const.py
gnsstoolbox/gnss_corr.py
gnsstoolbox/gnss_process.py
gnsstoolbox/gnsstools.py
gnsstoolbox/orbits.py
gnsstoolbox/rinex_o.py
gnsstoolbox/skyplot.py
gnsstoolbox.egg-info/PKG-INFO
gnsstoolbox.egg-info/SOURCES.txt
gnsstoolbox.egg-info/dependency_links.txt
gnsstoolbox.egg-info/requires.txt
gnsstoolbox.egg-info/top_level.txt