Metadata-Version: 2.1
Name: gnsstoolbox
Version: 1.2.10
Summary: Python GNSS processing package
Home-page: https://gitlab.com/jbeilin/pygnsstoolbox
Author: Jacques Beilin
Author-email: jacques.beilin@gmail.com
License: gpl
Platform: UNKNOWN
Classifier: Development Status :: 3 - Alpha
Classifier: Programming Language :: Python :: 3
Classifier: Programming Language :: Python :: 3.2
Classifier: Programming Language :: Python :: 3.3
Classifier: Programming Language :: Python :: 3.4
Classifier: Programming Language :: Python :: 3.5
Classifier: Programming Language :: Python :: 3.6
Classifier: Programming Language :: Python :: 3.7
Classifier: Programming Language :: Python :: 3.8
Classifier: Programming Language :: Python :: 3.9
Classifier: Programming Language :: Python :: 3.10
License-File: LICENCE.txt
